dpm_tools/__init__.py
dpm_tools/__version__.py
dpm_tools/io/__init__.py
dpm_tools/io/_io_utils.py
dpm_tools/io/_read_data.py
dpm_tools/io/_write_data.py
dpm_tools/metrics/__init__.py
dpm_tools/metrics/_feature_utils.py
dpm_tools/metrics/_fft_backends.py
dpm_tools/metrics/_maps.py
dpm_tools/metrics/_minkowski_coeff.py
dpm_tools/metrics/_minkowski_utils.py
dpm_tools/metrics/_scalars.py
dpm_tools/segmentation/__init__.py
dpm_tools/segmentation/_segment.py
dpm_tools/visualization/_3d_vis_utils.py
dpm_tools/visualization/__init__.py
dpm_tools/visualization/_plot_2d.py
dpm_tools/visualization/_plot_3d.py
dpm_tools/visualization/_vis_utils.py
dpm_tools-1.0.1.dist-info/licenses/LICENSE
dpm_tools-1.0.1.dist-info/METADATA
dpm_tools-1.0.1.dist-info/WHEEL
dpm_tools-1.0.1.dist-info/top_level.txt
dpm_tools-1.0.1.dist-info/RECORD
